django_storage/__init__.py
django_storage/qcloud.py
django_storage_qcloud/__init__.py
django_storage_qcloud/storage.py
django_storage_qcloud-0.2.1.dist-info/LICENSE
django_storage_qcloud-0.2.1.dist-info/METADATA
django_storage_qcloud-0.2.1.dist-info/WHEEL
django_storage_qcloud-0.2.1.dist-info/top_level.txt
django_storage_qcloud-0.2.1.dist-info/RECORD
