Metadata-Version: 2.1
Name: django-storage-qcloud
Version: 0.2.1
Summary: Django qcloud cos storage backend
Home-page: https://github.com/fordguo/django-storage-qcloud
Author: Ford
Author-email: agile.guo@gmail.com
License: MIT
Platform: UNKNOWN
Classifier: Development Status :: 3 - Alpha
Classifier: Programming Language :: Python :: 3.4
Classifier: Framework :: Django :: 2.2
Classifier: License :: OSI Approved :: MIT License
Classifier: Operating System :: OS Independent
Requires-Dist: django
Requires-Dist: cos-python-sdk-v5
